inference/__init__.py
inference/_version.py
inference/likelihoods.py
inference/plotting.py
inference/posterior.py
inference/priors.py
inference/approx/__init__.py
inference/approx/conditional.py
inference/gp/__init__.py
inference/gp/acquisition.py
inference/gp/covariance.py
inference/gp/inversion.py
inference/gp/mean.py
inference/gp/optimisation.py
inference/gp/regression.py
inference/mcmc/__init__.py
inference/mcmc/base.py
inference/mcmc/ensemble.py
inference/mcmc/gibbs.py
inference/mcmc/parallel.py
inference/mcmc/pca.py
inference/mcmc/utilities.py
inference/mcmc/hmc/__init__.py
inference/mcmc/hmc/epsilon.py
inference/mcmc/hmc/mass.py
inference/pdf/__init__.py
inference/pdf/base.py
inference/pdf/hdi.py
inference/pdf/kde.py
inference/pdf/unimodal.py
inference_tools-0.14.2.dist-info/licenses/LICENSE
inference_tools-0.14.2.dist-info/METADATA
inference_tools-0.14.2.dist-info/WHEEL
inference_tools-0.14.2.dist-info/top_level.txt
inference_tools-0.14.2.dist-info/RECORD
