Metadata-Version: 2.4
Name: inference-tools
Version: 0.14.2
Summary: A collection of python tools for Bayesian data analysis
Author-email: Chris Bowman <chris.bowman.physics@gmail.com>
License: MIT License
Project-URL: Homepage, https://github.com/C-bowman/inference-tools
Project-URL: Documentation, https://inference-tools.readthedocs.io/en/stable/
Classifier: Programming Language :: Python :: 3
Classifier: License :: OSI Approved :: MIT License
Classifier: Operating System :: OS Independent
Requires-Python: >=3.9
License-File: LICENSE
Requires-Dist: numpy>=1.20
Requires-Dist: scipy>=1.6.3
Requires-Dist: matplotlib>=3.4.2
Provides-Extra: tests
Requires-Dist: pytest>=3.3.0; extra == "tests"
Requires-Dist: pytest-cov>=3.0.0; extra == "tests"
Requires-Dist: pyqt5>=5.15; extra == "tests"
Requires-Dist: hypothesis>=6.24; extra == "tests"
Requires-Dist: freezegun>=1.1.0; extra == "tests"
Dynamic: license-file
